{
  "android-instant": {
    "REMOTE_SERVER_ROOT": "",
    "host": "",
    "pathPattern": "",
    "recordPath": "",
    "scheme": "https",
    "skipRecord": false
  },
  "appBundle": false,
  "baidugame": {
    "REMOTE_SERVER_ROOT": "",
    "appid": "testappid",
    "orientation": "portrait",
    "subContext": ""
  },
  "encryptJs": true,
  "excludeScenes": [
    "f1c9800a-7b7d-4902-98f4-f3f99d1f8574",
    "21a7df7c-94a6-4986-afdb-a43f8afa263e",
    "9f824dc3-778b-459a-8cad-e47bc9acbb1e",
    "e87d8911-0a24-4bb6-bf5a-f3c4ffbd5112"
  ],
  "fb-instant-games": {},
  "includeSDKBox": false,
  "inlineSpriteFrames": true,
  "inlineSpriteFrames_native": true,
  "md5Cache": false,
  "mergeStartScene": false,
  "optimizeHotUpdate": false,
  "orientation": {
    "landscapeLeft": true,
    "landscapeRight": true,
    "portrait": false,
    "upsideDown": false
  },
  "packageName": "org.cocos2d.Canves",
  "qqplay": {
    "REMOTE_SERVER_ROOT": "",
    "orientation": "portrait",
    "zip": false
  },
  "startScene": "0a6a651f-2867-44d8-88be-39343ed783c4",
  "title": "Rope",
  "webOrientation": "landscape",
  "wechatgame": {
    "REMOTE_SERVER_ROOT": "",
    "appid": "wx6ac3f5090a6b99c5",
    "orientation": "portrait",
    "separate_engine": false,
    "subContext": ""
  },
  "xxteaKey": "08b2b404-d96c-44",
  "zipCompressJs": true
}